easy_nodes/__init__.py
easy_nodes/comfy_types.py
easy_nodes/config_service.py
easy_nodes/easy_nodes.py
easy_nodes/llm_debugging.py
easy_nodes/log_streaming.py
easy_nodes/web/config_service.js
easy_nodes/web/easy_nodes.js
easy_nodes/web/llm_debugging.js
easy_nodes/web/log_streaming.js
easy_nodes/web/retain_previews.js
ComfyUI_EasyNodes-1.2.7.dist-info/LICENSE
ComfyUI_EasyNodes-1.2.7.dist-info/METADATA
ComfyUI_EasyNodes-1.2.7.dist-info/WHEEL
ComfyUI_EasyNodes-1.2.7.dist-info/top_level.txt
ComfyUI_EasyNodes-1.2.7.dist-info/RECORD
