Metadata-Version: 2.1
Name: ComfyUI-EasyNodes
Version: 1.2.7
Summary: Makes creating new nodes for ComfyUI a breeze.
Author-email: Andrew Harp <andrew.harp@gmail.com>
License: MIT License
Project-URL: Homepage, https://github.com/andrewharp/ComfyUI-EasyNodes
Project-URL: Bug Reports, https://github.com/andrewharp/ComfyUI-EasyNodes/issues
Project-URL: Source, https://github.com/andrewharp/ComfyUI-EasyNodes/
Requires-Python: >=3.10
License-File: LICENSE
Requires-Dist: torch
Requires-Dist: pillow
Requires-Dist: ansi2html
Requires-Dist: colorama
Requires-Dist: coloredlogs
Requires-Dist: numpy
Requires-Dist: openai
